aiokafka/__init__.py
aiokafka/abc.py
aiokafka/client.py
aiokafka/cluster.py
aiokafka/codec.py
aiokafka/conn.py
aiokafka/errors.py
aiokafka/helpers.py
aiokafka/partitioner.py
aiokafka/structs.py
aiokafka/util.py
aiokafka/admin/__init__.py
aiokafka/admin/client.py
aiokafka/admin/config_resource.py
aiokafka/admin/new_partitions.py
aiokafka/admin/new_topic.py
aiokafka/consumer/__init__.py
aiokafka/consumer/consumer.py
aiokafka/consumer/fetcher.py
aiokafka/consumer/group_coordinator.py
aiokafka/consumer/subscription_state.py
aiokafka/coordinator/__init__.py
aiokafka/coordinator/protocol.py
aiokafka/coordinator/assignors/__init__.py
aiokafka/coordinator/assignors/abstract.py
aiokafka/coordinator/assignors/range.py
aiokafka/coordinator/assignors/roundrobin.py
aiokafka/coordinator/assignors/sticky/__init__.py
aiokafka/coordinator/assignors/sticky/partition_movements.py
aiokafka/coordinator/assignors/sticky/sorted_set.py
aiokafka/coordinator/assignors/sticky/sticky_assignor.py
aiokafka/metrics/__init__.py
aiokafka/metrics/compound_stat.py
aiokafka/metrics/dict_reporter.py
aiokafka/metrics/kafka_metric.py
aiokafka/metrics/measurable.py
aiokafka/metrics/measurable_stat.py
aiokafka/metrics/metric_config.py
aiokafka/metrics/metric_name.py
aiokafka/metrics/metrics.py
aiokafka/metrics/metrics_reporter.py
aiokafka/metrics/quota.py
aiokafka/metrics/stat.py
aiokafka/metrics/stats/__init__.py
aiokafka/metrics/stats/avg.py
aiokafka/metrics/stats/count.py
aiokafka/metrics/stats/histogram.py
aiokafka/metrics/stats/max_stat.py
aiokafka/metrics/stats/min_stat.py
aiokafka/metrics/stats/percentile.py
aiokafka/metrics/stats/percentiles.py
aiokafka/metrics/stats/rate.py
aiokafka/metrics/stats/sampled_stat.py
aiokafka/metrics/stats/sensor.py
aiokafka/metrics/stats/total.py
aiokafka/producer/__init__.py
aiokafka/producer/message_accumulator.py
aiokafka/producer/producer.py
aiokafka/producer/sender.py
aiokafka/producer/transaction_manager.py
aiokafka/protocol/__init__.py
divyanx_aiokafka-0.10.6204991.dist-info/LICENSE
divyanx_aiokafka-0.10.6204991.dist-info/METADATA
divyanx_aiokafka-0.10.6204991.dist-info/WHEEL
divyanx_aiokafka-0.10.6204991.dist-info/top_level.txt
divyanx_aiokafka-0.10.6204991.dist-info/RECORD
