Metadata-Version: 2.1
Name: divyanx-aiokafka
Version: 0.10.6204991
Summary: Kafka integration with asyncio
Author-email: Andrew Svetlov <andrew.svetlov@gmail.com>
License: 
Project-URL: Documentation, http://aiokafka.readthedocs.org
Project-URL: Source, https://github.com/aio-libs/aiokafka
Project-URL: Changes, https://github.com/aio-libs/aiokafka/blob/master/CHANGES.rst
Classifier: License :: OSI Approved :: Apache Software License
Classifier: Intended Audience :: Developers
Classifier: Programming Language :: Python :: 3
Classifier: Programming Language :: Python :: 3.8
Classifier: Programming Language :: Python :: 3.9
Classifier: Programming Language :: Python :: 3.10
Classifier: Programming Language :: Python :: 3.11
Classifier: Programming Language :: Python :: 3.12
Classifier: Operating System :: OS Independent
Classifier: Topic :: System :: Networking
Classifier: Topic :: System :: Distributed Computing
Classifier: Framework :: AsyncIO
Classifier: Development Status :: 4 - Beta
Requires-Python: >=3.8
License-File: LICENSE
Requires-Dist: async-timeout
Requires-Dist: packaging
Provides-Extra: all
Requires-Dist: cramjam ; extra == 'all'
Requires-Dist: lz4 >=3.1.3 ; extra == 'all'
Requires-Dist: gssapi ; extra == 'all'
Provides-Extra: gssapi
Requires-Dist: gssapi ; extra == 'gssapi'
Provides-Extra: lz4
Requires-Dist: lz4 >=3.1.3 ; extra == 'lz4'
Provides-Extra: snappy
Requires-Dist: cramjam ; extra == 'snappy'
Provides-Extra: zstd
Requires-Dist: cramjam ; extra == 'zstd'
